openretina/__init__.py
openretina/py.typed
openretina/cli/__init__.py
openretina/cli/__main__.py
openretina/cli/create_data.py
openretina/cli/openretina_main.py
openretina/cli/train.py
openretina/cli/visualize_model_neurons.py
openretina/data_io/__init__.py
openretina/data_io/artificial_stimuli.py
openretina/data_io/base.py
openretina/data_io/base_dataloader.py
openretina/data_io/cyclers.py
openretina/data_io/h5_dataset_reader.py
openretina/data_io/hoefling_2024/__init__.py
openretina/data_io/hoefling_2024/constants.py
openretina/data_io/hoefling_2024/dataloaders.py
openretina/data_io/hoefling_2024/responses.py
openretina/data_io/hoefling_2024/stimuli.py
openretina/data_io/karamanlis_2024/__init__.py
openretina/data_io/karamanlis_2024/responses.py
openretina/data_io/karamanlis_2024/stimuli.py
openretina/data_io/maheswaranathan_2023/__init__.py
openretina/data_io/maheswaranathan_2023/constants.py
openretina/data_io/maheswaranathan_2023/responses.py
openretina/data_io/maheswaranathan_2023/stimuli.py
openretina/eval/metrics.py
openretina/eval/oracles.py
openretina/insilico/__init__.py
openretina/insilico/stimulus_optimization/__init__.py
openretina/insilico/stimulus_optimization/objective.py
openretina/insilico/stimulus_optimization/optimization_stopper.py
openretina/insilico/stimulus_optimization/optimizer.py
openretina/insilico/stimulus_optimization/regularizer.py
openretina/insilico/tuning_analyses/response_gradient.py
openretina/legacy/__init__.py
openretina/legacy/dev_models.py
openretina/legacy/models.py
openretina/models/__init__.py
openretina/models/core_readout.py
openretina/models/dev.py
openretina/models/linear_nonlinear.py
openretina/models/sparse_autoencoder.py
openretina/modules/__init__.py
openretina/modules/measures.py
openretina/modules/core/__init__.py
openretina/modules/core/base_core.py
openretina/modules/core/gru_core.py
openretina/modules/layers/__init__.py
openretina/modules/layers/convolutions.py
openretina/modules/layers/ensemble.py
openretina-1.0.0.dist-info/LICENSE
openretina-1.0.0.dist-info/METADATA
openretina-1.0.0.dist-info/WHEEL
openretina-1.0.0.dist-info/entry_points.txt
openretina-1.0.0.dist-info/top_level.txt
openretina-1.0.0.dist-info/RECORD
