Metadata-Version: 2.2
Name: openretina
Version: 1.0.0
Summary: Open source retina model architectures and training setups
Author: Federico D'Agostino, Thomas Zenkel, Larissa Höfling
Project-URL: Homepage, https://github.com/open-retina/open-retina
Project-URL: Issues, https://github.com/open-retina/open-retina/issues
Requires-Python: >=3.10
License-File: LICENSE
Requires-Dist: IPython
Requires-Dist: jaxtyping
Requires-Dist: matplotlib
Requires-Dist: numpy
Requires-Dist: pandas
Requires-Dist: seaborn
Requires-Dist: scipy
Requires-Dist: tenacity
Requires-Dist: tensorboard
Requires-Dist: torch
Requires-Dist: torchaudio
Requires-Dist: torchvision
Requires-Dist: einops
Requires-Dist: lightning
Requires-Dist: wandb
Requires-Dist: hydra-core
Requires-Dist: omegaconf
Requires-Dist: h5py
Requires-Dist: opencv-python-headless
Requires-Dist: imageio>=2.36
Requires-Dist: moviepy>=2.0.0
Requires-Dist: huggingface_hub>=0.25
Requires-Dist: jupyter
Requires-Dist: ipywidgets
Provides-Extra: dev
Requires-Dist: ruff>=0.9; extra == "dev"
Requires-Dist: mypy>=1.0; extra == "dev"
Requires-Dist: pytest; extra == "dev"
Requires-Dist: types-psutil; extra == "dev"
Requires-Dist: types-tqdm; extra == "dev"
Requires-Dist: types-PyYAML; extra == "dev"
Requires-Dist: types-requests; extra == "dev"
Requires-Dist: nbmake; extra == "dev"
Requires-Dist: jupyterlab; extra == "dev"
Provides-Extra: devmodels
Requires-Dist: neuralpredictors; extra == "devmodels"
